hddtemp.py
hddtemp-0.1.0.dist-info/DESCRIPTION.rst
hddtemp-0.1.0.dist-info/METADATA
hddtemp-0.1.0.dist-info/RECORD
hddtemp-0.1.0.dist-info/WHEEL
hddtemp-0.1.0.dist-info/metadata.json
hddtemp-0.1.0.dist-info/top_level.txt
